{
    "categories": [
        {
            "categoryName": "messages",
            "blocksInfo": {
                "activate": true,
                "activeBlocks": [
                    "messages_move_object"
                ]
            }
        },
        {
            "categoryName": "math",
            "blocksInfo": {
                "activate": true,
                "activeBlocks": [
                    "math_number"
                ]
            }
        },
        {
            "categoryName": "control",
            "blocksInfo": {
                "activate": false,
                "activeBlocks": [
                    "controls_ifelse",
                    "controls_for",
                    "controls_flow_statements"
                ]
            }
        }
    ]
}